{
  "manifestVersion": "3.2",
  "proxies": [
    {
      "address": "0x6B077Ac4CFBad676ae6aCdC4A6b0F637551fEB49",
      "txHash": "0x4e9565f6f8ebe294d45d0f6d3ad31fd5a13af9f39eca47a5359214e0674f3aaa",
      "kind": "uups"
    }
  ],
  "impls": {
    "28b3c093c9fe6303855ba0660590a8b059bb3b1a290df746c33629a32c456f8a": {
      "address": "0x8d5b55389EdfA4A54E7C6015e85b05A5A6381330",
      "txHash": "0x767d2f25eb1631c115d356d534daa9356f76bc923fc67c2c0b83d8b89dbc210e",
      "layout": {
        "solcVersion": "0.8.17",
        "storage": [
          {
            "label": "_initialized",
            "offset": 0,
            "slot": "0",
            "type": "t_uint8",
            "contract": "Initializable",
            "src": "@openzeppelin\\contracts-upgradeable\\proxy\\utils\\Initializable.sol:62",
            "retypedFrom": "bool"
          },
          {
            "label": "_initializing",
            "offset": 1,
            "slot": "0",
            "type": "t_bool",
            "contract": "Initializable",
            "src": "@openzeppelin\\contracts-upgradeable\\proxy\\utils\\Initializable.sol:67"
          },
          {
            "label": "__gap",
            "offset": 0,
            "slot": "1",
            "type": "t_array(t_uint256)50_storage",
            "contract": "ContextUpgradeable",
            "src": "@openzeppelin\\contracts-upgradeable\\utils\\ContextUpgradeable.sol:36"
          },
          {
            "label": "_paused",
            "offset": 0,
            "slot": "51",
            "type": "t_bool",
            "contract": "PausableUpgradeable",
            "src": "@openzeppelin\\contracts-upgradeable\\security\\PausableUpgradeable.sol:29"
          },
          {
            "label": "__gap",
            "offset": 0,
            "slot": "52",
            "type": "t_array(t_uint256)49_storage",
            "contract": "PausableUpgradeable",
            "src": "@openzeppelin\\contracts-upgradeable\\security\\PausableUpgradeable.sol:116"
          },
          {
            "label": "_owner",
            "offset": 0,
            "slot": "101",
            "type": "t_address",
            "contract": "OwnableUpgradeable",
            "src": "@openzeppelin\\contracts-upgradeable\\access\\OwnableUpgradeable.sol:22"
          },
          {
            "label": "__gap",
            "offset": 0,
            "slot": "102",
            "type": "t_array(t_uint256)49_storage",
            "contract": "OwnableUpgradeable",
            "src": "@openzeppelin\\contracts-upgradeable\\access\\OwnableUpgradeable.sol:94"
          },
          {
            "label": "__gap",
            "offset": 0,
            "slot": "151",
            "type": "t_array(t_uint256)50_storage",
            "contract": "ERC1967UpgradeUpgradeable",
            "src": "@openzeppelin\\contracts-upgradeable\\proxy\\ERC1967\\ERC1967UpgradeUpgradeable.sol:211"
          },
          {
            "label": "__gap",
            "offset": 0,
            "slot": "201",
            "type": "t_array(t_uint256)50_storage",
            "contract": "UUPSUpgradeable",
            "src": "@openzeppelin\\contracts-upgradeable\\proxy\\utils\\UUPSUpgradeable.sol:107"
          },
          {
            "label": "Trades",
            "offset": 0,
            "slot": "251",
            "type": "t_mapping(t_address,t_uint256)",
            "contract": "htlc",
            "src": "contracts\\HTLC.sol:43"
          },
          {
            "label": "TradeTrack",
            "offset": 0,
            "slot": "252",
            "type": "t_mapping(t_uint256,t_struct(Track)3022_storage)",
            "contract": "htlc",
            "src": "contracts\\HTLC.sol:44"
          },
          {
            "label": "TradeQueued",
            "offset": 0,
            "slot": "253",
            "type": "t_mapping(t_uint256,t_bool)",
            "contract": "htlc",
            "src": "contracts\\HTLC.sol:45"
          },
          {
            "label": "TradeTrackINRC",
            "offset": 0,
            "slot": "254",
            "type": "t_mapping(t_uint256,t_struct(Track)3022_storage)",
            "contract": "htlc",
            "src": "contracts\\HTLC.sol:46"
          },
          {
            "label": "TradeInprogress",
            "offset": 0,
            "slot": "255",
            "type": "t_mapping(t_uint256,t_bool)",
            "contract": "htlc",
            "src": "contracts\\HTLC.sol:49"
          },
          {
            "label": "INRC",
            "offset": 0,
            "slot": "256",
            "type": "t_address",
            "contract": "htlc",
            "src": "contracts\\HTLC.sol:62"
          }
        ],
        "types": {
          "t_address": {
            "label": "address",
            "numberOfBytes": "20"
          },
          "t_array(t_uint256)49_storage": {
            "label": "uint256[49]",
            "numberOfBytes": "1568"
          },
          "t_array(t_uint256)50_storage": {
            "label": "uint256[50]",
            "numberOfBytes": "1600"
          },
          "t_bool": {
            "label": "bool",
            "numberOfBytes": "1"
          },
          "t_mapping(t_address,t_uint256)": {
            "label": "mapping(address => uint256)",
            "numberOfBytes": "32"
          },
          "t_mapping(t_uint256,t_bool)": {
            "label": "mapping(uint256 => bool)",
            "numberOfBytes": "32"
          },
          "t_mapping(t_uint256,t_struct(Track)3022_storage)": {
            "label": "mapping(uint256 => struct htlc.Track)",
            "numberOfBytes": "32"
          },
          "t_string_storage": {
            "label": "string",
            "numberOfBytes": "32"
          },
          "t_struct(Track)3022_storage": {
            "label": "struct htlc.Track",
            "members": [
              {
                "label": "id",
                "type": "t_uint256",
                "offset": 0,
                "slot": "0"
              },
              {
                "label": "seller",
                "type": "t_address",
                "offset": 0,
                "slot": "1"
              },
              {
                "label": "blocktStamp",
                "type": "t_uint256",
                "offset": 0,
                "slot": "2"
              },
              {
                "label": "value",
                "type": "t_uint256",
                "offset": 0,
                "slot": "3"
              },
              {
                "label": "passphrase",
                "type": "t_string_storage",
                "offset": 0,
                "slot": "4"
              },
              {
                "label": "buyer",
                "type": "t_address",
                "offset": 0,
                "slot": "5"
              },
              {
                "label": "BuyerChainId",
                "type": "t_uint256",
                "offset": 0,
                "slot": "6"
              }
            ],
            "numberOfBytes": "224"
          },
          "t_uint256": {
            "label": "uint256",
            "numberOfBytes": "32"
          },
          "t_uint8": {
            "label": "uint8",
            "numberOfBytes": "1"
          }
        }
      }
    },
    "4f1cb41aaf5cdc36dea075dc6a5978746e29d788dde30382a9adb4cf157cd8da": {
      "address": "0x34434432244D48Bee0739861c1557A0CB55aBEB5",
      "txHash": "0xf797211d51b7db33bc66f2e08027306379b26eed69ae8741524e2c3a97e97bda",
      "layout": {
        "solcVersion": "0.8.17",
        "storage": [
          {
            "label": "_initialized",
            "offset": 0,
            "slot": "0",
            "type": "t_uint8",
            "contract": "Initializable",
            "src": "@openzeppelin\\contracts-upgradeable\\proxy\\utils\\Initializable.sol:62",
            "retypedFrom": "bool"
          },
          {
            "label": "_initializing",
            "offset": 1,
            "slot": "0",
            "type": "t_bool",
            "contract": "Initializable",
            "src": "@openzeppelin\\contracts-upgradeable\\proxy\\utils\\Initializable.sol:67"
          },
          {
            "label": "__gap",
            "offset": 0,
            "slot": "1",
            "type": "t_array(t_uint256)50_storage",
            "contract": "ERC1967UpgradeUpgradeable",
            "src": "@openzeppelin\\contracts-upgradeable\\proxy\\ERC1967\\ERC1967UpgradeUpgradeable.sol:211"
          },
          {
            "label": "__gap",
            "offset": 0,
            "slot": "51",
            "type": "t_array(t_uint256)50_storage",
            "contract": "UUPSUpgradeable",
            "src": "@openzeppelin\\contracts-upgradeable\\proxy\\utils\\UUPSUpgradeable.sol:107"
          },
          {
            "label": "__gap",
            "offset": 0,
            "slot": "101",
            "type": "t_array(t_uint256)50_storage",
            "contract": "ContextUpgradeable",
            "src": "@openzeppelin\\contracts-upgradeable\\utils\\ContextUpgradeable.sol:36"
          },
          {
            "label": "_owner",
            "offset": 0,
            "slot": "151",
            "type": "t_address",
            "contract": "OwnableUpgradeable",
            "src": "@openzeppelin\\contracts-upgradeable\\access\\OwnableUpgradeable.sol:22"
          },
          {
            "label": "__gap",
            "offset": 0,
            "slot": "152",
            "type": "t_array(t_uint256)49_storage",
            "contract": "OwnableUpgradeable",
            "src": "@openzeppelin\\contracts-upgradeable\\access\\OwnableUpgradeable.sol:94"
          },
          {
            "label": "_paused",
            "offset": 0,
            "slot": "201",
            "type": "t_bool",
            "contract": "PausableUpgradeable",
            "src": "@openzeppelin\\contracts-upgradeable\\security\\PausableUpgradeable.sol:29"
          },
          {
            "label": "__gap",
            "offset": 0,
            "slot": "202",
            "type": "t_array(t_uint256)49_storage",
            "contract": "PausableUpgradeable",
            "src": "@openzeppelin\\contracts-upgradeable\\security\\PausableUpgradeable.sol:116"
          },
          {
            "label": "stakers",
            "offset": 0,
            "slot": "251",
            "type": "t_array(t_address)dyn_storage",
            "contract": "LiquidityPool",
            "src": "contracts\\LiquidityPool.sol:44"
          },
          {
            "label": "USDStable",
            "offset": 0,
            "slot": "252",
            "type": "t_mapping(t_uint8,t_address)",
            "contract": "LiquidityPool",
            "src": "contracts\\LiquidityPool.sol:51"
          },
          {
            "label": "names",
            "offset": 0,
            "slot": "253",
            "type": "t_mapping(t_uint8,t_string_storage)",
            "contract": "LiquidityPool",
            "src": "contracts\\LiquidityPool.sol:52"
          },
          {
            "label": "liquidityPool",
            "offset": 0,
            "slot": "254",
            "type": "t_mapping(t_address,t_mapping(t_uint8,t_uint256))",
            "contract": "LiquidityPool",
            "src": "contracts\\LiquidityPool.sol:60"
          },
          {
            "label": "unstakedMax",
            "offset": 0,
            "slot": "255",
            "type": "t_mapping(t_address,t_mapping(t_uint8,t_bool))",
            "contract": "LiquidityPool",
            "src": "contracts\\LiquidityPool.sol:61"
          },
          {
            "label": "liquidityPoolStakes",
            "offset": 0,
            "slot": "256",
            "type": "t_mapping(t_address,t_mapping(t_uint8,t_uint256))",
            "contract": "LiquidityPool",
            "src": "contracts\\LiquidityPool.sol:72"
          },
          {
            "label": "totalLiquidity",
            "offset": 0,
            "slot": "257",
            "type": "t_uint256",
            "contract": "LiquidityPool",
            "src": "contracts\\LiquidityPool.sol:77"
          },
          {
            "label": "epochover",
            "offset": 0,
            "slot": "258",
            "type": "t_bool",
            "contract": "LiquidityPool",
            "src": "contracts\\LiquidityPool.sol:78"
          }
        ],
        "types": {
          "t_address": {
            "label": "address",
            "numberOfBytes": "20"
          },
          "t_array(t_address)dyn_storage": {
            "label": "address[]",
            "numberOfBytes": "32"
          },
          "t_array(t_uint256)49_storage": {
            "label": "uint256[49]",
            "numberOfBytes": "1568"
          },
          "t_array(t_uint256)50_storage": {
            "label": "uint256[50]",
            "numberOfBytes": "1600"
          },
          "t_bool": {
            "label": "bool",
            "numberOfBytes": "1"
          },
          "t_mapping(t_address,t_mapping(t_uint8,t_bool))": {
            "label": "mapping(address => mapping(uint8 => bool))",
            "numberOfBytes": "32"
          },
          "t_mapping(t_address,t_mapping(t_uint8,t_uint256))": {
            "label": "mapping(address => mapping(uint8 => uint256))",
            "numberOfBytes": "32"
          },
          "t_mapping(t_uint8,t_address)": {
            "label": "mapping(uint8 => address)",
            "numberOfBytes": "32"
          },
          "t_mapping(t_uint8,t_bool)": {
            "label": "mapping(uint8 => bool)",
            "numberOfBytes": "32"
          },
          "t_mapping(t_uint8,t_string_storage)": {
            "label": "mapping(uint8 => string)",
            "numberOfBytes": "32"
          },
          "t_mapping(t_uint8,t_uint256)": {
            "label": "mapping(uint8 => uint256)",
            "numberOfBytes": "32"
          },
          "t_string_storage": {
            "label": "string",
            "numberOfBytes": "32"
          },
          "t_uint256": {
            "label": "uint256",
            "numberOfBytes": "32"
          },
          "t_uint8": {
            "label": "uint8",
            "numberOfBytes": "1"
          }
        }
      }
    }
  }
}
